llama_index/experimental/__init__.py
llama_index/experimental/exec_utils.py
llama_index/experimental/nudge/__init__.py
llama_index/experimental/nudge/base.py
llama_index/experimental/param_tuner/__init__.py
llama_index/experimental/param_tuner/base.py
llama_index/experimental/query_engine/__init__.py
llama_index/experimental/query_engine/jsonalyze/__init__.py
llama_index/experimental/query_engine/jsonalyze/jsonalyze_query_engine.py
llama_index/experimental/query_engine/pandas/__init__.py
llama_index/experimental/query_engine/pandas/output_parser.py
llama_index/experimental/query_engine/pandas/pandas_query_engine.py
llama_index/experimental/query_engine/pandas/prompts.py
llama_index/experimental/retrievers/natural_language/README.md
llama_index/experimental/retrievers/natural_language/__init__.py
llama_index/experimental/retrievers/natural_language/nl_csv_retriever.py
llama_index/experimental/retrievers/natural_language/nl_data_frame_retriever.py
llama_index/experimental/retrievers/natural_language/nl_json_retriever.py
llama_index_experimental-0.6.3.dist-info/METADATA
llama_index_experimental-0.6.3.dist-info/WHEEL
llama_index_experimental-0.6.3.dist-info/licenses/LICENSE
llama_index_experimental-0.6.3.dist-info/RECORD
