Metadata-Version: 2.4
Name: llama-index-experimental
Version: 0.6.3
Summary: llama-index experimental package
Author-email: Your Name <you@example.com>
License-Expression: MIT
License-File: LICENSE
Requires-Python: <4.0,>=3.10
Requires-Dist: duckdb<2,>=1.0.0
Requires-Dist: llama-index-core<0.15,>=0.13.0
Requires-Dist: llama-index-finetuning<0.5,>=0.4
Requires-Dist: pandas<2.3.0
